opencv_camera/__init__.py
opencv_camera/bin/camera_calibrate.py
opencv_camera/bin/mjpeg_server.py
opencv_camera/bin/udp_client.py
opencv_camera/bin/udp_server.py
opencv_camera/bin/video_capture.py
opencv_camera/blurry.py
opencv_camera/color_space.py
opencv_camera/compression.py
opencv_camera/display/__init__.py
opencv_camera/display/flip_book.py
opencv_camera/display/lines.py
opencv_camera/display/stereo.py
opencv_camera/distortion.py
opencv_camera/mono/__init__.py
opencv_camera/mono/calibrate.py
opencv_camera/mono/camera.py
opencv_camera/parameters/__init__.py
opencv_camera/parameters/ex8029.py
opencv_camera/parameters/rpi_hq.py
opencv_camera/parameters/rpi_v2.py
opencv_camera/parameters/utils.py
opencv_camera/reproject.py
opencv_camera/save/__init__.py
opencv_camera/save/pointcloud.py
opencv_camera/save/video.py
opencv_camera/stereo/__init__.py
opencv_camera/stereo/calibrate.py
opencv_camera/stereo/camera.py
opencv_camera/stereo/fundamental_matrix.py
opencv_camera/stereo/pointcloud.py
opencv_camera/targets/__init__.py
opencv_camera/targets/chessboard.py
opencv_camera/threaded_camera.py
opencv_camera/undistort.py
opencv_camera-2023.1.7.dist-info/LICENSE
opencv_camera-2023.1.7.dist-info/WHEEL
opencv_camera-2023.1.7.dist-info/entry_points.txt
opencv_camera-2023.1.7.dist-info/METADATA
opencv_camera-2023.1.7.dist-info/RECORD
