Metadata-Version: 2.1
Name: opencv-camera
Version: 2023.1.7
Summary: An OpenCV camera library
Home-page: https://pypi.org/project/opencv_camera/
License: MIT
Keywords: computer vision,camera,calibration,opencv,jupyter,stereo camera,cv,cv2
Author: walchko
Author-email: walchko@users.noreply.github.com
Requires-Python: >=3.8
Classifier: Development Status :: 4 - Beta
Classifier: Framework :: Jupyter
Classifier: Framework :: Matplotlib
Classifier: Framework :: Robot Framework :: Library
Classifier: Intended Audience :: Developers
Classifier: Intended Audience :: Science/Research
Classifier: License :: OSI Approved :: MIT License
Classifier: Natural Language :: English
Classifier: Operating System :: OS Independent
Classifier: Programming Language :: Python :: 3
Classifier: Programming Language :: Python :: 3.8
Classifier: Programming Language :: Python :: 3.9
Classifier: Programming Language :: Python :: 3.10
Classifier: Programming Language :: Python :: 3.11
Classifier: Programming Language :: Python :: 3.10
Classifier: Programming Language :: Python :: 3.11
Classifier: Programming Language :: Python :: 3.8
Classifier: Programming Language :: Python :: 3.9
Classifier: Topic :: Scientific/Engineering
Classifier: Topic :: Scientific/Engineering :: Image Processing
Classifier: Topic :: Software Development :: Libraries
Classifier: Topic :: Software Development :: Libraries :: Application Frameworks
Classifier: Topic :: Software Development :: Libraries :: Python Modules
Requires-Dist: colorama
Requires-Dist: matplotlib
Requires-Dist: numpy
Requires-Dist: opencv-contrib-python
Requires-Dist: pyyaml
Project-URL: Repository, https://github.com/MomsFriendlyRobotCompany/opencv_camera
